setup.py
pylibcurl/__init__.py
pylibcurl/_stackless.py
pylibcurl/about.py
pylibcurl/base.py
pylibcurl/const.py
pylibcurl/curl.py
pylibcurl/exceptions.py
pylibcurl/iri2uri.py
pylibcurl/lib.py
pylibcurl/multi.py
pylibcurl/prototype.py
pylibcurl/share.py
pylibcurl/shortcuts.py
pylibcurl.egg-info/PKG-INFO
pylibcurl.egg-info/SOURCES.txt
pylibcurl.egg-info/dependency_links.txt
pylibcurl.egg-info/top_level.txt