Metadata-Version: 1.0
Name: pylibcurl
Version: 0.7.6
Summary: python ctypes curl library
Home-page: http://bitbucket.org/jungle/pylibcurl
Author: Askar Yusupov
Author-email: devex.soft@gmail.com
License: MIT
Download-URL: http://bitbucket.org/jungle/pylibcurl/downloads
Keywords: curl ctypes
Platform: UNKNOWN
Classifier: Development Status :: 4 - Beta
Classifier: Intended Audience :: Developers
Classifier: License :: OSI Approved :: MIT License
Classifier: Operating System :: OS Independent
Classifier: Programming Language :: Python
Classifier: Topic :: Internet :: WWW/HTTP
Classifier: Topic :: Software Development :: Libraries
